snowball/__init__.py
snowball/_version.py
snowball/backtest.py
snowball/components.py
snowball/report.py
snowball/rules.py
snowball-0.5.6.dist-info/licenses/LICENSE
snowball-0.5.6.dist-info/METADATA
snowball-0.5.6.dist-info/WHEEL
snowball-0.5.6.dist-info/top_level.txt
snowball-0.5.6.dist-info/RECORD
