Metadata-Version: 2.4
Name: Snowball
Version: 0.5.6
Summary: Investment strategy backtesting tool
Home-page: https://github.com/HongJunhyoung/Snowball
Author: Hong Junhyoung
Author-email: bellus77@gmail.com
License: MIT
Classifier: Operating System :: OS Independent
Requires-Python: >=3.8
License-File: LICENSE
Requires-Dist: numpy>=1.21.0
Requires-Dist: pandas>=1.3.5
Requires-Dist: scipy>=1.7.3
Requires-Dist: PyPortfolioOpt>=1.5.1
Requires-Dist: tqdm>=4.45.0
Requires-Dist: plotly>=5.1.0
Requires-Dist: kaleido>=0.2.1
Requires-Dist: Ipython
Dynamic: author
Dynamic: author-email
Dynamic: classifier
Dynamic: description
Dynamic: description-content-type
Dynamic: home-page
Dynamic: license
Dynamic: license-file
Dynamic: requires-dist
Dynamic: requires-python
Dynamic: summary
